shamir_mnemonic/__init__.py
shamir_mnemonic/cipher.py
shamir_mnemonic/cli.py
shamir_mnemonic/constants.py
shamir_mnemonic/recovery.py
shamir_mnemonic/rs1024.py
shamir_mnemonic/shamir.py
shamir_mnemonic/share.py
shamir_mnemonic/utils.py
shamir_mnemonic/wordlist.py
shamir_mnemonic/wordlist.txt
shamir_mnemonic-0.2.2.dist-info/LICENSE
shamir_mnemonic-0.2.2.dist-info/METADATA
shamir_mnemonic-0.2.2.dist-info/WHEEL
shamir_mnemonic-0.2.2.dist-info/entry_points.txt
shamir_mnemonic-0.2.2.dist-info/top_level.txt
shamir_mnemonic-0.2.2.dist-info/RECORD
