Metadata-Version: 2.1
Name: shamir-mnemonic
Version: 0.2.2
Summary: SLIP-39 Shamir Mnemonics
Home-page: https://github.com/trezor/python-shamir-mnemonic
Author: Satoshi Labs
Author-email: info@satoshilabs.com
License: UNKNOWN
Platform: UNKNOWN
Classifier: License :: OSI Approved :: MIT License
Classifier: Operating System :: POSIX :: Linux
Classifier: Operating System :: Microsoft :: Windows
Classifier: Operating System :: MacOS :: MacOS X
Classifier: Programming Language :: Python :: 3.6
Classifier: Programming Language :: Python :: 3 :: Only
Requires-Python: >=3.6
Requires-Dist: attrs
Requires-Dist: click (<9,>=7)
Requires-Dist: colorama
Provides-Extra: dev
Requires-Dist: black ; extra == 'dev'
Requires-Dist: flake8 ; extra == 'dev'
Requires-Dist: isort ; extra == 'dev'
Provides-Extra: tests
Requires-Dist: pytest ; extra == 'tests'
